main/__init__.py
main/hfautogen.py
hfautogen.py-1.3.dist-info/LICENSE
hfautogen.py-1.3.dist-info/METADATA
hfautogen.py-1.3.dist-info/WHEEL
hfautogen.py-1.3.dist-info/top_level.txt
hfautogen.py-1.3.dist-info/RECORD
