Metadata-Version: 2.1
Name: hfautogen.py
Version: 1.3
Summary: A seemless way to use HuggingFace Inference API with Autogen.
Home-page: https://github.com/Solonce/HFAutogen
Author: Solomon Ince
Author-email: solomon@solonce.com
Project-URL: Bug Tracker, https://github.com/Solonce/HFAutogen/issues
Classifier: Programming Language :: Python :: 3
Classifier: License :: OSI Approved :: MIT License
Classifier: Operating System :: OS Independent
Requires-Python: >=3.6
License-File: LICENSE
